bedms/__init__.py
bedms/_version.py
bedms/attr_standardizer.py
bedms/const.py
bedms/model.py
bedms/train.py
bedms/utils.py
bedms/utils_train.py
tests/__init__.py
tests/test_bedms.py
bedms-0.2.0.dist-info/LICENSE.txt
bedms-0.2.0.dist-info/METADATA
bedms-0.2.0.dist-info/WHEEL
bedms-0.2.0.dist-info/top_level.txt
bedms-0.2.0.dist-info/RECORD
