Metadata-Version: 2.1
Name: bedms
Version: 0.2.0
Summary: BEDMess attribute standardizer for metadata attribute standardization
Home-page: https://github.com/databio/bedmess/
Author: Saanika Tambe
License: BSD2
Keywords: project,metadata,bioinformatics
Classifier: Development Status :: 4 - Beta
Classifier: License :: OSI Approved :: BSD License
Classifier: Programming Language :: Python :: 3.8
Classifier: Programming Language :: Python :: 3.9
Classifier: Programming Language :: Python :: 3.10
Classifier: Programming Language :: Python :: 3.11
Classifier: Programming Language :: Python :: 3.12
Classifier: Topic :: Scientific/Engineering :: Bio-Informatics
License-File: LICENSE.txt
Requires-Dist: pandas
Requires-Dist: numpy
Requires-Dist: torch
Requires-Dist: sentence-transformers
Requires-Dist: pephubclient>=0.4.2
Requires-Dist: peppy>=0.40.6
Requires-Dist: matplotlib
Requires-Dist: seaborn
